{
  "data": [
    {
      "id": "1",
      "title": "Iphone 15 PRO MAX",
      "description": "Iphone 15 PRO MAX, 256GB Pink",
      "code": "IPH15",
      "price": 799.99,
      "status": true,
      "stock": 30,
      "category": "Celular",
      "thumbnails": [
        "images/iphone-15-pro-max-1.jpg",
        "images/iphone-15-pro-max-2.jpg"
      ]
    },
    {
      "id": "2",
      "title": "Iphone 20 PRO MAX",
      "description": "Iphone 20 PRO MAX, 256GB Pink",
      "code": "IPH20",
      "price": 999.99,
      "status": true,
      "stock": 30,
      "category": "Celular",
      "thumbnails": [
        "images/iphone-20-pro-max-1.jpg",
        "images/iphone-20-pro-max-2.jpg"
      ]
    }
  ]
}